aiostdlib/__init__.py
aiostdlib/internal/__init__.py
aiostdlib/internal/core/__init__.py
aiostdlib/internal/core/asyncio.py
aiostdlib/internal/core/executor.py
aiostdlib/internal/core/workers.py
aiostdlib/internal/stdlib/__init__.py
aiostdlib/internal/stdlib/json.py
aiostdlib/internal/stdlib/os.py
aiostdlib/internal/stdlib/ospath.py
aiostdlib/internal/stdlib/tomllib.py
aiostdlib/internal/utils/__init__.py
aiostdlib/internal/utils/os.py
aiostdlib/internal/utils/typing.py
aiostdlib/json.py
aiostdlib/os/__init__.py
aiostdlib/os/path.py
aiostdlib/py.typed
aiostdlib/tomllib.py
aiostdlib-0.2.0.dist-info/AUTHORS
aiostdlib-0.2.0.dist-info/LICENSE
aiostdlib-0.2.0.dist-info/METADATA
aiostdlib-0.2.0.dist-info/WHEEL
aiostdlib-0.2.0.dist-info/RECORD
