Metadata-Version: 2.1
Name: aiostdlib
Version: 0.2.0
Summary: Only the standard library... but asynchronous!
Home-page: https://github.com/syubogdanov/aiostdlib
License: MIT
Keywords: async,json,ntpath,os,posixpath,python,stdlib,tomllib
Author: Sergei Y. Bogdanov
Author-email: syubogdanov@outlook.com
Maintainer: Sergei Y. Bogdanov
Maintainer-email: syubogdanov@outlook.com
Requires-Python: >=3.9,<3.14
Classifier: Development Status :: 2 - Pre-Alpha
Classifier: Intended Audience :: Developers
Classifier: License :: OSI Approved :: MIT License
Classifier: Operating System :: OS Independent
Classifier: Programming Language :: Python
Classifier: Programming Language :: Python :: 3
Classifier: Programming Language :: Python :: 3.9
Classifier: Programming Language :: Python :: 3.10
Classifier: Programming Language :: Python :: 3.11
Classifier: Programming Language :: Python :: 3.12
Classifier: Programming Language :: Python :: 3.13
Requires-Dist: backlib (>=0.2.1,<0.3.0)
Requires-Dist: typing-extensions (>=4.12,<5.0)
Project-URL: Documentation, https://aiostdlib.readthedocs.io
Project-URL: Repository, https://github.com/syubogdanov/aiostdlib
